file_validator/__init__.py
file_validator/constants.py
file_validator/exceptions.py
file_validator/forms.py
file_validator/models.py
file_validator/utils.py
file_validator/validators.py
file_validator/widgets.py
file_validator/templates/file_validator/file_input_widget.html
file_validator-1.0.9.dist-info/AUTHORS.md
file_validator-1.0.9.dist-info/LICENSE
file_validator-1.0.9.dist-info/METADATA
file_validator-1.0.9.dist-info/WHEEL
file_validator-1.0.9.dist-info/entry_points.txt
file_validator-1.0.9.dist-info/top_level.txt
file_validator-1.0.9.dist-info/RECORD
