Metadata-Version: 2.1
Name: file-validator
Version: 1.0.9
Summary: Python validation library to validate files using type, mime, extension, magic numbers and size ✅
Home-page: https://github.com/file-validator/file-validator
Author: Reza Shakeri
Author-email: rzashakeri@outlook.com
License: MIT license
Project-URL: Documentation, https://file-validator.github.io/
Project-URL: Homepage, https://github.com/file-validator
Project-URL: Issue tracker, https://github.com/file-validator/file-validator/issues
Project-URL: Release notes, https://github.com/file-validator/file-validator/releases
Project-URL: Source, https://github.com/file-validator/file-validator
Project-URL: Discussions, https://github.com/orgs/file-validator/discussions
Project-URL: History Of Changes, https://file-validator.github.io/docs/history/
Keywords: file_validator,file,validator,image_validator,audio_validator,video_validator,django
Classifier: Development Status :: 5 - Production/Stable
Classifier: Intended Audience :: Developers
Classifier: License :: OSI Approved :: MIT License
Classifier: Natural Language :: English
Classifier: Programming Language :: Python :: 3.8
Classifier: Programming Language :: Python :: 3.9
Classifier: Programming Language :: Python :: 3.10
Classifier: Programming Language :: Python :: 3.11
Classifier: Framework :: Django
Classifier: Topic :: Multimedia
Classifier: Topic :: Multimedia :: Sound/Audio
Classifier: Topic :: Multimedia :: Video
Classifier: Topic :: Security
Classifier: Topic :: Software Development :: Libraries
Requires-Python: >=3.8
License-File: LICENSE
License-File: AUTHORS.md
Requires-Dist: humanize (==4.4.0)
Requires-Dist: filetype (==1.1.0)
Requires-Dist: termcolor (==1.1.0)
Requires-Dist: puremagic (==1.14)
Requires-Dist: python-dotenv (==0.21.1)
Requires-Dist: django
Requires-Dist: python-magic (==0.4.27) ; platform_system != "Windows"
Requires-Dist: python-magic-bin (==0.4.14) ; platform_system == "Windows"
